Labs/lab3-3/sim/judge.v
// fill the code


module Judge (
    input clk,
    input rstn,
    input [31:0] multiplicand,
    input [31:0] multiplier,
    input start,
    input [63:0] product,
    input finish,
    output reg error
);

    reg [31:0] multiplicand_reg;
    reg [31:0] multiplier_reg;
    always@(posedge clk or negedge rstn)begin
        if(~rstn)begin
            multiplicand_reg <= 32'b0;
            multiplier_reg <= 32'b0;
        end else if(start)begin
            multiplicand_reg <= multiplicand;
            multiplier_reg <= multiplier;
        end
    end

    always@(posedge clk or negedge rstn)begin
        if(~rstn)begin
            error <= 1'b0;
        end else begin
            if(finish)begin
                if(mul_judge(multiplicand_reg,multiplier_reg,product)==32'b1)begin
                    error <= 1'b0;
                end else begin
                    error <= 1'b1;
                end
            end
        end
    end
    
endmodule //Judge

Labs/lab3/lab3/lab3-3/submit/Multiplier.sv
module Multiplier #(
    parameter LEN = 32
) (
    input clk,
    input rst,
    input [LEN-1:0] multiplicand,
    input [LEN-1:0] multiplier,
    input start,
    
    output logic [LEN*2-1:0] product,
    output logic finish
);

    localparam PRODUCT_LEN = LEN*2;
    logic [LEN-1:0] multiplicand_reg;
    logic [PRODUCT_LEN:0] product_reg;
    localparam CNT_LEN = $clog2(LEN);
    localparam CNT_NUM = LEN - 1;
    typedef enum [1:0] {IDLE, WORK, FINAL} fsm_state;
    fsm_state fsm_state_reg;
    logic [CNT_LEN+1:0] Count;
    logic [LEN:0] high_product_temp;

    always @(posedge clk or negedge rst) begin
        if(rst) begin
            fsm_state_reg<=IDLE;
        end else begin
            case(fsm_state_reg)
                IDLE:begin 
                    finish<=1'b0;
                    if(start)begin
                        product_reg={(PRODUCT_LEN+1){1'b0}};
                        multiplicand_reg<=multiplicand;
                        product_reg[CNT_NUM:0]=multiplier;
                        product_reg[PRODUCT_LEN-1:LEN]={LEN{1'b0}};
                        Count<=0;
                        fsm_state_reg<=WORK;
                        high_product_temp={(LEN+1){1'b0}};
                    end else begin
                        fsm_state_reg<=IDLE;
                    end
                end
                WORK:begin
                    if(Count==LEN)begin
                        fsm_state_reg<=FINAL;
                    end else begin
                        if(product_reg[0] & 1)begin
                            high_product_temp={1'b0,product_reg[PRODUCT_LEN-1:LEN]}+{1'b0,multiplicand_reg};
                        end else begin
                            high_product_temp={1'b0,product_reg[PRODUCT_LEN-1:LEN]};
                        end
                        {product_reg[PRODUCT_LEN:LEN],product_reg[CNT_NUM:0]}={high_product_temp,product_reg[CNT_NUM:0]}>>1;
                        Count<=Count+1;
                    end
                
                end
                FINAL:begin
                    product<=product_reg[PRODUCT_LEN-1:0];
                    finish<=1'b1;
                    fsm_state_reg<=IDLE;
                    Count<=0;
                end
                default:;
            endcase
        end
    end
endmodule

Labs/lab3/lab3/lab3-3/sim/testbench.v
module Testbench;

    reg clk;
    reg rst;
    reg [31:0] multiplicand;
    reg [31:0] multiplier;
    reg start;
    reg low_pro;
    wire [63:0] product;
    wire finish;
    integer i;
    integer seed=114514;
    initial begin
        clk=0;
        rst=1;
        #20;
        rst=0;
            for(i=0;i<16;i=i+1)begin
                start=1;
                multiplicand = $random(seed);
                multiplier = $random(seed);
                #10;
                start=0;
                @(posedge finish); 
                #25;
            end
        $display("success!!!");
        $finish;
    end

    always begin
        #5;
        clk=~clk;
    end

    Multiplier #(
        .LEN(32)
    ) mul (
        .clk(clk),
        .rst(rst),
        .multiplicand(multiplicand),
        .multiplier(multiplier),
        .start(start),
        
        .product(product),
        .finish(finish)
    );

    `ifdef VERILATE
		initial begin
			$dumpfile({`TOP_DIR,"/Testbench.vcd"});
			$dumpvars(0,dut);
			$dumpon;
		end

        wire error;
        Judge judge(
            .clk(clk),
            .rstn(~rst),
            .multiplicand(multiplicand),
            .multiplier(multiplier),
            .start(start),
            .product(product),
            .finish(finish),
            .error(error)
        );

        always@(negedge clk)begin
            if(error)begin
                $display("fail!!!");
                $finish;
            end
        end
    `endif
    
endmodule

Labs/lab3-3/build/verilate/Testbench.vcd
$version Generated by VerilatedVcd $end
$timescale 10ps $end
 $scope module TOP $end
  $scope module Testbench $end
   $var wire 1 8 clk $end
   $var wire 1 # rst $end
   $var wire 32 $ multiplicand [31:0] $end
   $var wire 32 % multiplier [31:0] $end
   $var wire 1 & start $end
   $var wire 1 9 low_pro $end
   $var wire 64 - product [63:0] $end
   $var wire 1 / finish $end
   $var wire 32 ' i [31:0] $end
   $var wire 32 ( seed [31:0] $end
   $var wire 1 * error $end
   $scope module judge $end
    $var wire 1 8 clk $end
    $var wire 1 ) rstn $end
    $var wire 32 $ multiplicand [31:0] $end
    $var wire 32 % multiplier [31:0] $end
    $var wire 1 & start $end
    $var wire 64 - product [63:0] $end
    $var wire 1 / finish $end
    $var wire 1 * error $end
    $var wire 32 + multiplicand_reg [31:0] $end
    $var wire 32 , multiplier_reg [31:0] $end
   $upscope $end
   $scope module mul $end
    $var wire 32 : LEN [31:0] $end
    $var wire 1 8 clk $end
    $var wire 1 # rst $end
    $var wire 32 $ multiplicand [31:0] $end
    $var wire 32 % multiplier [31:0] $end
    $var wire 1 & start $end
    $var wire 64 - product [63:0] $end
    $var wire 1 / finish $end
    $var wire 32 ; PRODUCT_LEN [31:0] $end
    $var wire 32 0 multiplicand_reg [31:0] $end
    $var wire 65 1 product_reg [64:0] $end
    $var wire 32 < CNT_LEN [31:0] $end
    $var wire 32 = CNT_NUM [31:0] $end
    $var wire 2 4 fsm_state_reg [1:0] $end
    $var wire 7 5 Count [6:0] $end
    $var wire 33 6 high_product_temp [32:0] $end
   $upscope $end
  $upscope $end
 $upscope $end
$enddefinitions $end


#0
1#
b00000000000000000000000000000000 $
b00000000000000000000000000000000 %
0&
b00000000000000000000000000000000 '
b00000000000000011011111101010010 (
0)
0*
b00000000000000000000000000000000 +
b00000000000000000000000000000000 ,
b0000000000000000000000000000000000000000000000000000000000000000 -
0/
b00000000000000000000000000000000 0
b00000000000000000000000000000000000000000000000000000000000000000 1
b00 4
b0000000 5
b000000000000000000000000000000000 6
08
09
b00000000000000000000000000100000 :
b00000000000000000000000001000000 ;
b00000000000000000000000000000101 <
b00000000000000000000000000011111 =
#500
18
#1000
08
#1500
18
#2000
0#
b10101001000000000000000011011111 $
b01010010000000000000000110111111 %
1&
b00000000000001101111110101001000 (
1)
b10101001000000000000000011011111 0
b00000000000000000000000000000000001010010000000000000000110111111 1
b01 4
08
#2500
b10101001000000000000000011011111 +
b01010010000000000000000110111111 ,
b00101010010000000000000000110111110101001000000000000000011011111 1
b0000001 5
b010101001000000000000000011011111 6
18
#3000
0&
08
#3500
b00111111011000000000000001010011101010100100000000000000001101111 1
b0000010 5
b011111101100000000000000101001110 6
18
#4000
08
#4500
b01001001111100000000000001100001100101010010000000000000000110111 1
b0000011 5
b100100111110000000000000110000110 6
18
#5000
08
#5500
b01001111001110000000000001101000100010101001000000000000000011011 1
b0000100 5
b100111100111000000000000110100010 6
18
#6000
08
#6500
b01010001110111000000000001101100000001010100100000000000000001101 1
b0000101 5
b101000111011100000000000110110000 6
18
#7000
08
#7500
b01010011001011100000000001101101110000101010010000000000000000110 1
b0000110 5
b101001100101110000000000110110111 6
18
#8000
08
#8500
b00101001100101110000000000110110111000010101001000000000000000011 1
b0000111 5
b010100110010111000000000011011011 6
18
#9000
08
#9500
b00111111000010111000000001010011001100001010100100000000000000001 1
b0001000 5
b011111100001011100000000101001100 6
18
#10000
08
#10500
b01001001110001011100000001100001010110000101010010000000000000000 1
b0001001 5
b100100111000101110000000110000101 6
18
#11000
08
#11500
b00100100111000101110000000110000101011000010101001000000000000000 1
b0001010 5
b010010011100010111000000011000010 6
18
#12000
08
#12500
b00010010011100010111000000011000010101100001010100100000000000000 1
b0001011 5
b001001001110001011100000001100001 6
18
#13000
08
#13500
b00001001001110001011100000001100001010110000101010010000000000000 1
b0001100 5
b000100100111000101110000000110000 6
18
#14000
08
#14500
b00000100100111000101110000000110000101011000010101001000000000000 1
b0001101 5
b000010010011100010111000000011000 6
18
#15000
08
#15500
b00000010010011100010111000000011000010101100001010100100000000000 1
b0001110 5
b000001001001110001011100000001100 6
18
#16000
08
#16500
b00000001001001110001011100000001100001010110000101010010000000000 1
b0001111 5
b000000100100111000101110000000110 6
18
#17000
08
#17500
b00000000100100111000101110000000110000101011000010101001000000000 1
b0010000 5
b000000010010011100010111000000011 6
18
#18000
08
#18500
b00000000010010011100010111000000011000010101100001010100100000000 1
b0010001 5
b000000001001001110001011100000001 6
18
#19000
08
#19500
b00000000001001001110001011100000001100001010110000101010010000000 1
b0010010 5
b000000000100100111000101110000000 6
18
#20000
08
#20500
b00000000000100100111000101110000000110000101011000010101001000000 1
b0010011 5
b000000000010010011100010111000000 6
18
#21000
08
#21500
b00000000000010010011100010111000000011000010101100001010100100000 1
b0010100 5
b000000000001001001110001011100000 6
18
#22000
08
#22500
b00000000000001001001110001011100000001100001010110000101010010000 1
b0010101 5
b000000000000100100111000101110000 6
18
#23000
08
#23500
b00000000000000100100111000101110000000110000101011000010101001000 1
b0010110 5
b000000000000010010011100010111000 6
18
#24000
08
#24500
b00000000000000010010011100010111000000011000010101100001010100100 1
b0010111 5
b000000000000001001001110001011100 6
18
#25000
08
#25500
b00000000000000001001001110001011100000001100001010110000101010010 1
b0011000 5
b000000000000000100100111000101110 6
18
#26000
08
#26500
b00000000000000000100100111000101110000000110000101011000010101001 1
b0011001 5
b000000000000000010010011100010111 6
18
#27000
08
#27500
b00101010010000000010010100011010101000000011000010101100001010100 1
b0011010 5
b010101001000000001001010001101010 6
18
#28000
08
#28500
b00010101001000000001001010001101010100000001100001010110000101010 1
b0011011 5
b001010100100000000100101000110101 6
18
#29000
08
#29500
b00001010100100000000100101000110101010000000110000101011000010101 1
b0011100 5
b000101010010000000010010100011010 6
18
#30000
08
#30500
b00101111100010000000010011011011000101000000011000010101100001010 1
b0011101 5
b010111110001000000001001101101100 6
18
#31000
08
#31500
b00010111110001000000001001101101100010100000001100001010110000101 1
b0011110 5
b001011111000100000000100110110110 6
18
#32000
08
#32500
b00110110001000100000000101101110100001010000000110000101011000010 1
b0011111 5
b011011000100010000000010110111010 6
18
#33000
08
#33500
b00011011000100010000000010110111010000101000000011000010101100001 1
b0100000 5
b001101100010001000000001011011101 6
18
#34000
08
#34500
b10 4
18
#35000
08
#35500
b0011011000100010000000010110111010000101000000011000010101100001 -
1/
b00 4
b0000000 5
18
#36000
08
#36500
0/
18
#37000
08
#37500
18
#38000
b10100100000000000000001101111110 $
b01001000000000000000011011111101 %
1&
b00000000000000000000000000000001 '
b00000000000110111111010100100000 (
08
#38500
b10100100000000000000001101111110 +
b01001000000000000000011011111101 ,
b10100100000000000000001101111110 0
b00000000000000000000000000000000001001000000000000000011011111101 1
b01 4
b000000000000000000000000000000000 6
18
#39000
0&
08
#39500
b00101001000000000000000011011111100100100000000000000001101111110 1
b0000001 5
b010100100000000000000001101111110 6
18
#40000
08
#40500
b00010100100000000000000001101111110010010000000000000000110111111 1
b0000010 5
b001010010000000000000000110111111 6
18
#41000
08
#41500
b00110011010000000000000100010111011001001000000000000000011011111 1
b0000011 5
b011001101000000000000010001011101 6
18
#42000
08
#42500
b01000010101000000000000101101011001100100100000000000000001101111 1
b0000100 5
b100001010100000000000010110101100 6
18
#43000
08
#43500
b01001010010100000000000110010101000110010010000000000000000110111 1
b0000101 5
b100101001010000000000011001010100 6
18
#44000
08
#44500
b01001110001010000000000110101010000011001001000000000000000011011 1
b0000110 5
b100111000101000000000011010101000 6
18
#45000
08
#45500
b01010000000101000000000110110100100001100100100000000000000001101 1
b0000111 5
b101000000010100000000011011010010 6
18
#46000
08
#46500
b01010001000010100000000110111001110000110010010000000000000000110 1
b0001000 5
b101000100001010000000011011100111 6
18
#47000
08
#47500
b00101000100001010000000011011100111000011001001000000000000000011 1
b0001001 5
b010100010000101000000001101110011 6
18
#48000
08
#48500
b00111101010000101000000101001101111100001100100100000000000000001 1
b0001010 5
b011110101000010100000010100110111 6
18
#49000
08
#49500
b01000111101000010100000110000110011110000110010010000000000000000 1
b0001011 5
b100011110100001010000011000011001 6
18
#50000
08
#50500
b00100011110100001010000011000011001111000011001001000000000000000 1
b0001100 5
b010001111010000101000001100001100 6
18
#51000
08
#51500
b00010001111010000101000001100001100111100001100100100000000000000 1
b0001101 5
b001000111101000010100000110000110 6
18
#52000
08
#52500
b00001000111101000010100000110000110011110000110010010000000000000 1
b0001110 5
b000100011110100001010000011000011 6
18
#53000
08
#53500
b00000100011110100001010000011000011001111000011001001000000000000 1
b0001111 5
b000010001111010000101000001100001 6
18
#54000
08
#54500
b00000010001111010000101000001100001100111100001100100100000000000 1
b0010000 5
b000001000111101000010100000110000 6
18
#55000
08
#55500
b00000001000111101000010100000110000110011110000110010010000000000 1
b0010001 5
b000000100011110100001010000011000 6
18
#56000
08
#56500
b00000000100011110100001010000011000011001111000011001001000000000 1
b0010010 5
b000000010001111010000101000001100 6
18
#57000
08
#57500
b00000000010001111010000101000001100001100111100001100100100000000 1
b0010011 5
b000000001000111101000010100000110 6
18
#58000
08
#58500
b00000000001000111101000010100000110000110011110000110010010000000 1
b0010100 5
b000000000100011110100001010000011 6
18
#59000
08
#59500
b00000000000100011110100001010000011000011001111000011001001000000 1
b0010101 5
b000000000010001111010000101000001 6
18
#60000
08
#60500
b00000000000010001111010000101000001100001100111100001100100100000 1
b0010110 5
b000000000001000111101000010100000 6
18
#61000
08
#61500
b00000000000001000111101000010100000110000110011110000110010010000 1
b0010111 5
b000000000000100011110100001010000 6
18
#62000
08
#62500
b00000000000000100011110100001010000011000011001111000011001001000 1
b0011000 5
b000000000000010001111010000101000 6
18
#63000
08
#63500
b00000000000000010001111010000101000001100001100111100001100100100 1
b0011001 5
b000000000000001000111101000010100 6
18
#64000
08
#64500
b00000000000000001000111101000010100000110000110011110000110010010 1
b0011010 5
b000000000000000100011110100001010 6
18
#65000
08
#65500
b00000000000000000100011110100001010000011000011001111000011001001 1
b0011011 5
b000000000000000010001111010000101 6
18
#66000
08
#66500
b00101001000000000010010010110000001000001100001100111100001100100 1
b0011100 5
b010100100000000001001001011000000 6
18
#67000
08
#67500
b00010100100000000001001001011000000100000110000110011110000110010 1
b0011101 5
b001010010000000000100100101100000 6
18
#68000
08
#68500
b00001010010000000000100100101100000010000011000011001111000011001 1
b0011110 5
b000101001000000000010010010110000 6
18
#69000
08
#69500
b00101110001000000000010101110101100001000001100001100111100001100 1
b0011111 5
b010111000100000000001010111010110 6
18
#70000
08
#70500
b00010111000100000000001010111010110000100000110000110011110000110 1
b0100000 5
b001011100010000000000101011101011 6
18
#71000
08
#71500
b10 4
18
#72000
08
#72500
b0010111000100000000001010111010110000100000110000110011110000110 -
1/
b00 4
b0000000 5
18
#73000
08
#73500
0/
18
#74000
08
#74500
18
#75000
b10010000000000000000110111111010 $
b00100000000000000001101111110101 %
1&
b00000000000000000000000000000010 '
b00000000011011111101010010000000 (
08
#75500
b10010000000000000000110111111010 +
b00100000000000000001101111110101 ,
b10010000000000000000110111111010 0
b00000000000000000000000000000000000100000000000000001101111110101 1
b01 4
b000000000000000000000000000000000 6
18
#76000
0&
08
#76500
b00100100000000000000001101111110100010000000000000000110111111010 1
b0000001 5
b010010000000000000000110111111010 6
18
#77000
08
#77500
b00010010000000000000000110111111010001000000000000000011011111101 1
b0000010 5
b001001000000000000000011011111101 6
18
#78000
08
#78500
b00101101000000000000010001011110001000100000000000000001101111110 1
b0000011 5
b010110100000000000001000101111000 6
18
#79000
08
#79500
b00010110100000000000001000101111000100010000000000000000110111111 1
b0000100 5
b001011010000000000000100010111100 6
18
#80000
08
#80500
b00101111010000000000010010010110000010001000000000000000011011111 1
b0000101 5
b010111101000000000001001001011000 6
18
#81000
08
#81500
b00111011101000000000010111001001100001000100000000000000001101111 1
b0000110 5
b011101110100000000001011100100110 6
18
#82000
08
#82500
b01000001110100000000011001100011010000100010000000000000000110111 1
b0000111 5
b100000111010000000001100110001101 6
18
#83000
08
#83500
b01000100111010000000011010110000001000010001000000000000000011011 1
b0001000 5
b100010011101000000001101011000000 6
18
#84000
08
#84500
b01000110011101000000011011010110100100001000100000000000000001101 1
b0001001 5
b100011001110100000001101101011010 6
18
#85000
08
#85500
b01000111001110100000011011101001110010000100010000000000000000110 1
b0001010 5
b100011100111010000001101110100111 6
18
#86000
08
#86500
b00100011100111010000001101110100111001000010001000000000000000011 1
b0001011 5
b010001110011101000000110111010011 6
18
#87000
08
#87500
b00110101110011101000010100111000111100100001000100000000000000001 1
b0001100 5
b011010111001110100001010011100011 6
18
#88000
08
#88500
b00111110111001110100011000011010111110010000100010000000000000000 1
b0001101 5
b011111011100111010001100001101011 6
18
#89000
08
#89500
b00011111011100111010001100001101011111001000010001000000000000000 1
b0001110 5
b001111101110011101000110000110101 6
18
#90000
08
#90500
b00001111101110011101000110000110101111100100001000100000000000000 1
b0001111 5
b000111110111001110100011000011010 6
18
#91000
08
#91500
b00000111110111001110100011000011010111110010000100010000000000000 1
b0010000 5
b000011111011100111010001100001101 6
18
#92000
08
#92500
b00000011111011100111010001100001101011111001000010001000000000000 1
b0010001 5
b000001111101110011101000110000110 6
18
#93000
08
#93500
b00000001111101110011101000110000110101111100100001000100000000000 1
b0010010 5
b000000111110111001110100011000011 6
18
#94000
08
#94500
b00000000111110111001110100011000011010111110010000100010000000000 1
b0010011 5
b000000011111011100111010001100001 6
18
#95000
08
#95500
b00000000011111011100111010001100001101011111001000010001000000000 1
b0010100 5
b000000001111101110011101000110000 6
18
#96000
08
#96500
b00000000001111101110011101000110000110101111100100001000100000000 1
b0010101 5
b000000000111110111001110100011000 6
18
#97000
08
#97500
b00000000000111110111001110100011000011010111110010000100010000000 1
b0010110 5
b000000000011111011100111010001100 6
18
#98000
08
#98500
b00000000000011111011100111010001100001101011111001000010001000000 1
b0010111 5
b000000000001111101110011101000110 6
18
#99000
08
#99500
b00000000000001111101110011101000110000110101111100100001000100000 1
b0011000 5
b000000000000111110111001110100011 6
18
#100000
08
#100500
b00000000000000111110111001110100011000011010111110010000100010000 1
b0011001 5
b000000000000011111011100111010001 6
18
#101000
08
#101500
b00000000000000011111011100111010001100001101011111001000010001000 1
b0011010 5
b000000000000001111101110011101000 6
18
#102000
08
#102500
b00000000000000001111101110011101000110000110101111100100001000100 1
b0011011 5
b000000000000000111110111001110100 6
18
#103000
08
#103500
b00000000000000000111110111001110100011000011010111110010000100010 1
b0011100 5
b000000000000000011111011100111010 6
18
#104000
08
#104500
b00000000000000000011111011100111010001100001101011111001000010001 1
b0011101 5
b000000000000000001111101110011101 6
18
#105000
08
#105500
b00100100000000000010001011110010001000110000110101111100100001000 1
b0011110 5
b010010000000000001000101111001000 6
18
#106000
08
#106500
b00010010000000000001000101111001000100011000011010111110010000100 1
b0011111 5
b001001000000000000100010111100100 6
18
#107000
08
#107500
b00001001000000000000100010111100100010001100001101011111001000010 1
b0100000 5
b000100100000000000010001011110010 6
18
#108000
08
#108500
b10 4
18
#109000
08
#109500
b0001001000000000000100010111100100010001100001101011111001000010 -
1/
b00 4
b0000000 5
18
#110000
08
#110500
0/
18
#111000
08
#111500
18
#112000
b01000000000000000011011111101010 $
b10000000000000000110111111010100 %
1&
b00000000000000000000000000000011 '
b00000001101111110101001000000000 (
08
#112500
b01000000000000000011011111101010 +
b10000000000000000110111111010100 ,
b01000000000000000011011111101010 0
b00000000000000000000000000000000010000000000000000110111111010100 1
b01 4
b000000000000000000000000000000000 6
18
#113000
0&
08
#113500
b00000000000000000000000000000000001000000000000000011011111101010 1
b0000001 5
18
#114000
08
#114500
b00000000000000000000000000000000000100000000000000001101111110101 1
b0000010 5
18
#115000
08
#115500
b00010000000000000000110111111010100010000000000000000110111111010 1
b0000011 5
b001000000000000000011011111101010 6
18
#116000
08
#116500
b00001000000000000000011011111101010001000000000000000011011111101 1
b0000100 5
b000100000000000000001101111110101 6
18
#117000
08
#117500
b00010100000000000001000101111001001000100000000000000001101111110 1
b0000101 5
b001010000000000000100010111100100 6
18
#118000
08
#118500
b00001010000000000000100010111100100100010000000000000000110111111 1
b0000110 5
b000101000000000000010001011110010 6
18
#119000
08
#119500
b00010101000000000001001001011000110010001000000000000000011011111 1
b0000111 5
b001010100000000000100100101100011 6
18
#120000
08
#120500
b00011010100000000001011100100110111001000100000000000000001101111 1
b0001000 5
b001101010000000000101110010011011 6
18
#121000
08
#121500
b00011101010000000001100110001101111100100010000000000000000110111 1
b0001001 5
b001110101000000000110011000110111 6
18
#122000
08
#122500
b00011110101000000001101011000001011110010001000000000000000011011 1
b0001010 5
b001111010100000000110101100000101 6
18
#123000
08
#123500
b00011111010100000001101101011011001111001000100000000000000001101 1
b0001011 5
b001111101010000000110110101101100 6
18
#124000
08
#124500
b00011111101010000001101110101000000111100100010000000000000000110 1
b0001100 5
b001111110101000000110111010100000 6
18
#125000
08
#125500
b00001111110101000000110111010100000011110010001000000000000000011 1
b0001101 5
b000111111010100000011011101010000 6
18
#126000
08
#126500
b00010111111010100001010011100100100001111001000100000000000000001 1
b0001110 5
b001011111101010000101001110010010 6
18
#127000
08
#127500
b00011011111101010001100001101100110000111100100010000000000000000 1
b0001111 5
b001101111110101000110000110110011 6
18
#128000
08
#128500
b00001101111110101000110000110110011000011110010001000000000000000 1
b0010000 5
b000110111111010100011000011011001 6
18
#129000
08
#129500
b00000110111111010100011000011011001100001111001000100000000000000 1
b0010001 5
b000011011111101010001100001101100 6
18
#130000
08
#130500
b00000011011111101010001100001101100110000111100100010000000000000 1
b0010010 5
b000001101111110101000110000110110 6
18
#131000
08
#131500
b00000001101111110101000110000110110011000011110010001000000000000 1
b0010011 5
b000000110111111010100011000011011 6
18
#132000
08
#132500
b00000000110111111010100011000011011001100001111001000100000000000 1
b0010100 5
b000000011011111101010001100001101 6
18
#133000
08
#133500
b00000000011011111101010001100001101100110000111100100010000000000 1
b0010101 5
b000000001101111110101000110000110 6
18
#134000
08
#134500
b00000000001101111110101000110000110110011000011110010001000000000 1
b0010110 5
b000000000110111111010100011000011 6
18
#135000
08
#135500
b00000000000110111111010100011000011011001100001111001000100000000 1
b0010111 5
b000000000011011111101010001100001 6
18
#136000
08
#136500
b00000000000011011111101010001100001101100110000111100100010000000 1
b0011000 5
b000000000001101111110101000110000 6
18
#137000
08
#137500
b00000000000001101111110101000110000110110011000011110010001000000 1
b0011001 5
b000000000000110111111010100011000 6
18
#138000
08
#138500
b00000000000000110111111010100011000011011001100001111001000100000 1
b0011010 5
b000000000000011011111101010001100 6
18
#139000
08
#139500
b00000000000000011011111101010001100001101100110000111100100010000 1
b0011011 5
b000000000000001101111110101000110 6
18
#140000
08
#140500
b00000000000000001101111110101000110000110110011000011110010001000 1
b0011100 5
b000000000000000110111111010100011 6
18
#141000
08
#141500
b00000000000000000110111111010100011000011011001100001111001000100 1
b0011101 5
b000000000000000011011111101010001 6
18
#142000
08
#142500
b00000000000000000011011111101010001100001101100110000111100100010 1
b0011110 5
b000000000000000001101111110101000 6
18
#143000
08
#143500
b00000000000000000001101111110101000110000110110011000011110010001 1
b0011111 5
b000000000000000000110111111010100 6
18
#144000
08
#144500
b00010000000000000001101111110101000011000011011001100001111001000 1
b0100000 5
b001000000000000000110111111010100 6
18
#145000
08
#145500
b10 4
18
#146000
08
#146500
b0010000000000000001101111110101000011000011011001100001111001000 -
1/
b00 4
b0000000 5
18
#147000
08
#147500
0/
18
#148000
08
#148500
18
#149000
b00000000000000001101111110101001 $
b00000000000000011011111101010010 %
1&
b00000000000000000000000000000100 '
b00000110111111010100100000000000 (
08
#149500
b00000000000000001101111110101001 +
b00000000000000011011111101010010 ,
b00000000000000001101111110101001 0
b00000000000000000000000000000000000000000000000011011111101010010 1
b01 4
b000000000000000000000000000000000 6
18
#150000
0&
08
#150500
b00000000000000000000000000000000000000000000000001101111110101001 1
b0000001 5
18
#151000
08
#151500
b00000000000000000011011111101010010000000000000000110111111010100 1
b0000010 5
b000000000000000001101111110101001 6
18
#152000
08
#152500
b00000000000000000001101111110101001000000000000000011011111101010 1
b0000011 5
b000000000000000000110111111010100 6
18
#153000
08
#153500
b00000000000000000000110111111010100100000000000000001101111110101 1
b0000100 5
b000000000000000000011011111101010 6
18
#154000
08
#154500
b00000000000000000011111011100111100010000000000000000110111111010 1
b0000101 5
b000000000000000001111101110011110 6
18
#155000
08
#155500
b00000000000000000001111101110011110001000000000000000011011111101 1
b0000110 5
b000000000000000000111110111001111 6
18
#156000
08
#156500
b00000000000000000100011110100100001000100000000000000001101111110 1
b0000111 5
b000000000000000010001111010010000 6
18
#157000
08
#157500
b00000000000000000010001111010010000100010000000000000000110111111 1
b0001000 5
b000000000000000001000111101001000 6
18
#158000
08
#158500
b00000000000000000100100111010011010010001000000000000000011011111 1
b0001001 5
b000000000000000010010011101001101 6
18
#159000
08
#159500
b00000000000000000101110011010011111001000100000000000000001101111 1
b0001010 5
b000000000000000010111001101001111 6
18
#160000
08
#160500
b00000000000000000110011001010100001100100010000000000000000110111 1
b0001011 5
b000000000000000011001100101010000 6
18
#161000
08
#161500
b00000000000000000110101100010100010110010001000000000000000011011 1
b0001100 5
b000000000000000011010110001010001 6
18
#162000
08
#162500
b00000000000000000110110101110100011011001000100000000000000001101 1
b0001101 5
b000000000000000011011010111010001 6
18
#163000
08
#163500
b00000000000000000110111010100100011101100100010000000000000000110 1
b0001110 5
b000000000000000011011101010010001 6
18
#164000
08
#164500
b00000000000000000011011101010010001110110010001000000000000000011 1
b0001111 5
b000000000000000001101110101001000 6
18
#165000
08
#165500
b00000000000000000101001110010011010111011001000100000000000000001 1
b0010000 5
b000000000000000010100111001001101 6
18
#166000
08
#166500
b00000000000000000110000110110011111011101100100010000000000000000 1
b0010001 5
b000000000000000011000011011001111 6
18
#167000
08
#167500
b00000000000000000011000011011001111101110110010001000000000000000 1
b0010010 5
b000000000000000001100001101100111 6
18
#168000
08
#168500
b00000000000000000001100001101100111110111011001000100000000000000 1
b0010011 5
b000000000000000000110000110110011 6
18
#169000
08
#169500
b00000000000000000000110000110110011111011101100100010000000000000 1
b0010100 5
b000000000000000000011000011011001 6
18
#170000
08
#170500
b00000000000000000000011000011011001111101110110010001000000000000 1
b0010101 5
b000000000000000000001100001101100 6
18
#171000
08
#171500
b00000000000000000000001100001101100111110111011001000100000000000 1
b0010110 5
b000000000000000000000110000110110 6
18
#172000
08
#172500
b00000000000000000000000110000110110011111011101100100010000000000 1
b0010111 5
b000000000000000000000011000011011 6
18
#173000
08
#173500
b00000000000000000000000011000011011001111101110110010001000000000 1
b0011000 5
b000000000000000000000001100001101 6
18
#174000
08
#174500
b00000000000000000000000001100001101100111110111011001000100000000 1
b0011001 5
b000000000000000000000000110000110 6
18
#175000
08
#175500
b00000000000000000000000000110000110110011111011101100100010000000 1
b0011010 5
b000000000000000000000000011000011 6
18
#176000
08
#176500
b00000000000000000000000000011000011011001111101110110010001000000 1
b0011011 5
b000000000000000000000000001100001 6
18
#177000
08
#177500
b00000000000000000000000000001100001101100111110111011001000100000 1
b0011100 5
b000000000000000000000000000110000 6
18
#178000
08
#178500
b00000000000000000000000000000110000110110011111011101100100010000 1
b0011101 5
b000000000000000000000000000011000 6
18
#179000
08
#179500
b00000000000000000000000000000011000011011001111101110110010001000 1
b0011110 5
b000000000000000000000000000001100 6
18
#180000
08
#180500
b00000000000000000000000000000001100001101100111110111011001000100 1
b0011111 5
b000000000000000000000000000000110 6
18
#181000
08
#181500
b00000000000000000000000000000000110000110110011111011101100100010 1
b0100000 5
b000000000000000000000000000000011 6
18
#182000
08
#182500
b10 4
18
#183000
08
#183500
b0000000000000000000000000000000110000110110011111011101100100010 -
1/
b00 4
b0000000 5
18
#184000
08
#184500
0/
18
#185000
08
#185500
18
#186000
b00000000000000110111111010100100 $
b00000000000001101111110101001000 %
1&
b00000000000000000000000000000101 '
b00011011111101010010000000000000 (
08
#186500
b00000000000000110111111010100100 +
b00000000000001101111110101001000 ,
b00000000000000110111111010100100 0
b00000000000000000000000000000000000000000000001101111110101001000 1
b01 4
b000000000000000000000000000000000 6
18
#187000
0&
08
#187500
b00000000000000000000000000000000000000000000000110111111010100100 1
b0000001 5
18
#188000
08
#188500
b00000000000000000000000000000000000000000000000011011111101010010 1
b0000010 5
18
#189000
08
#189500
b00000000000000000000000000000000000000000000000001101111110101001 1
b0000011 5
18
#190000
08
#190500
b00000000000000001101111110101001000000000000000000110111111010100 1
b0000100 5
b000000000000000110111111010100100 6
18
#191000
08
#191500
b00000000000000000110111111010100100000000000000000011011111101010 1
b0000101 5
b000000000000000011011111101010010 6
18
#192000
08
#192500
b00000000000000000011011111101010010000000000000000001101111110101 1
b0000110 5
b000000000000000001101111110101001 6
18
#193000
08
#193500
b00000000000000001111101110011110001000000000000000000110111111010 1
b0000111 5
b000000000000000111110111001111000 6
18
#194000
08
#194500
b00000000000000000111110111001111000100000000000000000011011111101 1
b0001000 5
b000000000000000011111011100111100 6
18
#195000
08
#195500
b00000000000000010001111010010000100010000000000000000001101111110 1
b0001001 5
b000000000000001000111101001000010 6
18
#196000
08
#196500
b00000000000000001000111101001000010001000000000000000000110111111 1
b0001010 5
b000000000000000100011110100100001 6
18
#197000
08
#197500
b00000000000000010010011101001101001000100000000000000000011011111 1
b0001011 5
b000000000000001001001110100110100 6
18
#198000
08
#198500
b00000000000000010111001101001111100100010000000000000000001101111 1
b0001100 5
b000000000000001011100110100111110 6
18
#199000
08
#199500
b00000000000000011001100101010000110010001000000000000000000110111 1
b0001101 5
b000000000000001100110010101000011 6
18
#200000
08
#200500
b00000000000000011010110001010001011001000100000000000000000011011 1
b0001110 5
b000000000000001101011000101000101 6
18
#201000
08
#201500
b00000000000000011011010111010001101100100010000000000000000001101 1
b0001111 5
b000000000000001101101011101000110 6
18
#202000
08
